{
  "schema": "construction_os_registration_audit_report",
  "version": "2.0.0",
  "pass_id": "registry-native-expansion-construction-os-registry",
  "pass_timestamp": "2026-03-29T12:00:00Z",
  "status": "FINAL",
  "audit_entries": [
    {"repo_name":"VTI_TM","architectural_class":"GOVERNANCE_REFERENCE","topology_node_type":"GOVERNANCE","readiness":"READY","notes":"Group A base.","blockers":[],"induction_status":"INDUCED","canonical_scope":"ACTIVE_NATIVE","inferred_relations":[]},
    {"repo_name":"Construction_Application_OS","architectural_class":"APPLICATION_SURFACE","topology_node_type":"APPLICATION","readiness":"READY","notes":"Group A base.","blockers":[],"induction_status":"INDUCED","canonical_scope":"ACTIVE_NATIVE","inferred_relations":[]},
    {"repo_name":"Construction_Cognitive_Bus","architectural_class":"COGNITIVE_BUS","topology_node_type":"BUS","readiness":"READY","notes":"Group A base.","blockers":[],"induction_status":"INDUCED","canonical_scope":"ACTIVE_NATIVE","inferred_relations":[]},
    {"repo_name":"Construction_Assembly_Kernel","architectural_class":"DOMAIN_KERNEL","topology_node_type":"KERNEL","readiness":"READY","notes":"Group A base.","blockers":[],"induction_status":"INDUCED","canonical_scope":"ACTIVE_NATIVE","inferred_relations":[]},
    {"repo_name":"Construction_Awareness_Cache","architectural_class":"AWARENESS","topology_node_type":"CACHE","readiness":"READY","notes":"Group A base.","blockers":[],"induction_status":"INDUCED","canonical_scope":"ACTIVE_NATIVE","inferred_relations":[]},
    {"repo_name":"Construction_Assistant","architectural_class":"ASSISTANT","topology_node_type":"ASSISTANT","readiness":"READY","notes":"Group A base.","blockers":[],"induction_status":"INDUCED","canonical_scope":"ACTIVE_NATIVE","inferred_relations":[]},
    {"repo_name":"Construction_Kernel","architectural_class":"CORE_KERNEL","topology_node_type":"KERNEL","readiness":"READY","notes":"Group A base.","blockers":[],"induction_status":"INDUCED","canonical_scope":"ACTIVE_NATIVE","inferred_relations":[]},
    {"repo_name":"Construction_Workforce_OS","architectural_class":"DOMAIN_KERNEL","topology_node_type":"KERNEL","readiness":"READY","notes":"Group A base.","blockers":[],"induction_status":"INDUCED","canonical_scope":"ACTIVE_NATIVE","inferred_relations":[]},
    {"repo_name":"Construction_Intelligence_Workers","architectural_class":"WORKER_FLEET","topology_node_type":"WORKERS","readiness":"READY","notes":"Group A base.","blockers":[],"induction_status":"INDUCED","canonical_scope":"ACTIVE_NATIVE","inferred_relations":[]},
    {"repo_name":"Construction_OS_Registry","architectural_class":"REGISTRY","topology_node_type":"REGISTRY","readiness":"READY","notes":"Group A base. Self-registration.","blockers":[],"induction_status":"INDUCED","canonical_scope":"ACTIVE_NATIVE","inferred_relations":[]},
    {"repo_name":"construction_dna","architectural_class":"DNA_LAYER","topology_node_type":"DNA","readiness":"READY","notes":"Group A base.","blockers":[],"induction_status":"INDUCED","canonical_scope":"ACTIVE_NATIVE","inferred_relations":[]},
    {"repo_name":"Construction_Pattern_Language_OS","architectural_class":"PATTERN_SYSTEM","topology_node_type":"PATTERN","readiness":"READY","notes":"Group A base.","blockers":[],"induction_status":"INDUCED","canonical_scope":"ACTIVE_NATIVE","inferred_relations":[]},
    {"repo_name":"Construction_Reference_Intelligence","architectural_class":"REFERENCE_INTELLIGENCE","topology_node_type":"REFERENCE","readiness":"READY","notes":"Group A base.","blockers":[],"induction_status":"INDUCED","canonical_scope":"ACTIVE_NATIVE","inferred_relations":[]},
    {"repo_name":"Construction_Runtime","architectural_class":"RUNTIME","topology_node_type":"RUNTIME","readiness":"READY_WITH_NOTES","notes":"Group A base. Prior-run evidence.","blockers":["Direct observation not available"],"induction_status":"INDUCED","canonical_scope":"ACTIVE_NATIVE","inferred_relations":[]},
    {"repo_name":"Construction_Atlas","architectural_class":"DOMAIN_KERNEL","topology_node_type":"REFERENCE","readiness":"READY_WITH_NOTES","notes":"Group B native. Purified spatial context layer. Classified from platform_inventory.json.","blockers":["Not directly observed this session"],"induction_status":"INDUCED","canonical_scope":"ACTIVE_NATIVE","inferred_relations":["REGISTERS_TO Construction_OS_Registry (inferred)","SUPPORTS Construction_Runtime (inferred from platform_inventory.json)","SUPPORTS Construction_Application_OS (inferred from platform_inventory.json)","SUPPORTS Construction_ALEXANDER_Engine (inferred from platform_inventory.json)"]},
    {"repo_name":"Construction_Chemistry_Kernel","architectural_class":"DOMAIN_KERNEL","topology_node_type":"KERNEL","readiness":"READY_WITH_NOTES","notes":"Group B native. Domain sub-kernel. Classified from 2026-03-22 system map.","blockers":["Not directly observed"],"induction_status":"INDUCED","canonical_scope":"ACTIVE_NATIVE","inferred_relations":["REGISTERS_TO Construction_OS_Registry (inferred)"]},
    {"repo_name":"Construction_Scope_Kernel","architectural_class":"DOMAIN_KERNEL","topology_node_type":"KERNEL","readiness":"READY_WITH_NOTES","notes":"Group B native. Domain sub-kernel. Classified from 2026-03-22 system map.","blockers":["Not directly observed"],"induction_status":"INDUCED","canonical_scope":"ACTIVE_NATIVE","inferred_relations":["REGISTERS_TO Construction_OS_Registry (inferred)"]},
    {"repo_name":"Construction_Material_Kernel","architectural_class":"DOMAIN_KERNEL","topology_node_type":"KERNEL","readiness":"READY_WITH_NOTES","notes":"Group B native. Domain sub-kernel. Classified from 2026-03-22 system map.","blockers":["Not directly observed"],"induction_status":"INDUCED","canonical_scope":"ACTIVE_NATIVE","inferred_relations":["REGISTERS_TO Construction_OS_Registry (inferred)"]},
    {"repo_name":"Construction_Specification_Kernel","architectural_class":"DOMAIN_KERNEL","topology_node_type":"KERNEL","readiness":"READY_WITH_NOTES","notes":"Group B native. Domain sub-kernel. Classified from 2026-03-22 system map.","blockers":["Not directly observed"],"induction_status":"INDUCED","canonical_scope":"ACTIVE_NATIVE","inferred_relations":["REGISTERS_TO Construction_OS_Registry (inferred)"]},
    {"repo_name":"Construction_ALEXANDER_Engine","architectural_class":"DOMAIN_KERNEL","topology_node_type":"WORKERS","readiness":"READY_WITH_NOTES","notes":"Group B native. Ring 2 pattern intelligence. Classified from platform_inventory.json.","blockers":["Not directly observed"],"induction_status":"INDUCED","canonical_scope":"ACTIVE_NATIVE","inferred_relations":["REGISTERS_TO Construction_OS_Registry (inferred)","READS_FROM Construction_Pattern_Language_OS (inferred)","READS_FROM Construction_Atlas (inferred)","READS_FROM Construction_Reference_Intelligence (inferred)","EMITS_TO Construction_Cognitive_Bus (inferred)"]},
    {"repo_name":"ShopDrawing_Compiler","architectural_class":"DOMAIN_KERNEL","topology_node_type":"REFERENCE","readiness":"READY_WITH_NOTES","notes":"Group B native. Compilation capability. Classified from 2026-03-22 system map.","blockers":["Not directly observed"],"induction_status":"INDUCED","canonical_scope":"ACTIVE_NATIVE","inferred_relations":["REGISTERS_TO Construction_OS_Registry (inferred)","SUPPORTS Construction_Runtime (inferred)"]},
    {"repo_name":"Universal_Truth_Kernel","architectural_class":"GOVERNANCE_REFERENCE","topology_node_type":"REFERENCE","readiness":"READY_WITH_NOTES","notes":"Group C attached. Upstream root doctrine.","blockers":["External upstream repo"],"induction_status":"REFERENCE_ATTACHED","canonical_scope":"ATTACHED_REFERENCE","inferred_relations":["SUPPORTS Construction_Kernel (inferred)"]},
    {"repo_name":"ValidKernel-Governance","architectural_class":"GOVERNANCE_REFERENCE","topology_node_type":"REFERENCE","readiness":"READY_WITH_NOTES","notes":"Group C attached. ValidKernel governance.","blockers":["External upstream repo"],"induction_status":"REFERENCE_ATTACHED","canonical_scope":"ATTACHED_REFERENCE","inferred_relations":["SUPPORTS Construction_OS_Registry (inferred)"]},
    {"repo_name":"ValidKernel_Geometry_Kernel","architectural_class":"GOVERNANCE_REFERENCE","topology_node_type":"REFERENCE","readiness":"READY_WITH_NOTES","notes":"Group C attached. Spatial primitives provider.","blockers":["External upstream repo"],"induction_status":"REFERENCE_ATTACHED","canonical_scope":"ATTACHED_REFERENCE","inferred_relations":["SUPPORTS Construction_Kernel (inferred from platform_inventory.json)","SUPPORTS Construction_Atlas (inferred from platform_inventory.json)"]},
    {"repo_name":"ValidKernel_Patterns","architectural_class":"GOVERNANCE_REFERENCE","topology_node_type":"REFERENCE","readiness":"READY_WITH_NOTES","notes":"Group C attached. Structural patterns lineage parent.","blockers":["External upstream repo"],"induction_status":"REFERENCE_ATTACHED","canonical_scope":"ATTACHED_REFERENCE","inferred_relations":["SUPPORTS Construction_Pattern_Language_OS (inferred from platform_inventory.json)"]},
    {"repo_name":"ValidKernelOS_VKBUS","architectural_class":"COGNITIVE_BUS","topology_node_type":"REFERENCE","readiness":"READY_WITH_NOTES","notes":"Group C attached. Governance observation/relay.","blockers":["Not directly observed"],"induction_status":"REFERENCE_ATTACHED","canonical_scope":"ATTACHED_REFERENCE","inferred_relations":["SUPPORTS Construction_Cognitive_Bus (inferred)"]},
    {"repo_name":"ValidKernel_Registry","architectural_class":"REGISTRY","topology_node_type":"REFERENCE","readiness":"READY_WITH_NOTES","notes":"Group C attached. Global kernel lineage authority.","blockers":["Not directly observed"],"induction_status":"REFERENCE_ATTACHED","canonical_scope":"ATTACHED_REFERENCE","inferred_relations":["SUPPORTS Construction_OS_Registry (inferred)"]},
    {"repo_name":"trade_os","architectural_class":"RUNTIME","topology_node_type":"REFERENCE","readiness":"READY_WITH_NOTES","notes":"Group C attached. External contractor operations platform.","blockers":["External platform"],"induction_status":"REFERENCE_ATTACHED","canonical_scope":"ATTACHED_REFERENCE","inferred_relations":["READS_FROM Construction_Workforce_OS (inferred)"]},
    {"repo_name":"SUPA-SAINT","architectural_class":"RUNTIME","topology_node_type":"REFERENCE","readiness":"READY_WITH_NOTES","notes":"Group C attached. External building-envelope delivery pipeline.","blockers":["External platform"],"induction_status":"REFERENCE_ATTACHED","canonical_scope":"ATTACHED_REFERENCE","inferred_relations":["READS_FROM Construction_Runtime (inferred)"]}
  ]
}